pysh/__init__.py
pysh/api/__init__.py
pysh/api/client.py
pysh/api/schema.py
pysh_client-0.1.1.dist-info/LICENSE
pysh_client-0.1.1.dist-info/METADATA
pysh_client-0.1.1.dist-info/WHEEL
pysh_client-0.1.1.dist-info/top_level.txt
pysh_client-0.1.1.dist-info/RECORD
